interator/__init__.py
interator/interator.py
interator-0.3.dist-info/LICENSE.txt
interator-0.3.dist-info/METADATA
interator-0.3.dist-info/WHEEL
interator-0.3.dist-info/top_level.txt
interator-0.3.dist-info/RECORD
