Metadata-Version: 2.1
Name: interator
Version: 0.3
Summary: Integer sequence generation and related conditional tests.
Home-page: https://github.com/willleskowitz/interator
Author: Will Leskowitz
Author-email: willleskowitz@gmail.com
License: MIT
Keywords: iterator,integer,sequence,generator,Fibonacci,Lucas,generalizations,prime,numbers,polygonal,tests
Platform: UNKNOWN
Classifier: Programming Language :: Python :: 3
Classifier: License :: OSI Approved :: MIT License
Classifier: Operating System :: OS Independent
Requires-Python: >=3.7
Requires-Dist: numpy
